{"is_source_file": false, "format": "", "description": "", "external_files": [], "external_methods": [], "published": [], "classes": [], "methods": [], "calls": [], "search-terms": [], "state": 2, "file_id": 2, "knowledge_revision": 9, "git_revision": "e2506a7e04e8e7f7a61ebd25d17b60b742483c6d", "hash": "0bf7dc4c297d7cd66528228ae2c77f8d", "format-version": 4, "code-base-name": "tic_tac_toe_frontend", "filename": "tic_tac_toe_frontend/package.json", "revision_history": [{"9": "e2506a7e04e8e7f7a61ebd25d17b60b742483c6d"}]}